IRS_toolkit/__init__.py
IRS_toolkit/core/__init__.py
IRS_toolkit/core/cash_flow.py
IRS_toolkit/core/curve/__init__.py
IRS_toolkit/core/curve/compounded.py
IRS_toolkit/core/curve/yield_curve.py
IRS_toolkit/core/leg/__init__.py
IRS_toolkit/core/leg/fix_leg.py
IRS_toolkit/core/leg/float_leg.py
IRS_toolkit/core/swap.py
IRS_toolkit/options/__init__.py
IRS_toolkit/options/blackscholes.py
IRS_toolkit/options/swaption.py
IRS_toolkit/utils/__init__.py
IRS_toolkit/utils/constants.py
IRS_toolkit/utils/core.py
IRS_toolkit/utils/financial.py
IRS_toolkit/utils/schedule.py
irs_toolkit-0.2.2.dist-info/METADATA
irs_toolkit-0.2.2.dist-info/WHEEL
irs_toolkit-0.2.2.dist-info/RECORD
