Metadata-Version: 2.3
Name: IRS_toolkit
Version: 0.2.2
Summary: Package to compute and price swap
Author: alan.dromas
Author-email: alan.dromas@qonto.com
Requires-Python: >=3.11,<3.13
Classifier: Programming Language :: Python :: 3
Classifier: Programming Language :: Python :: 3.11
Classifier: Programming Language :: Python :: 3.12
Requires-Dist: flask (>=3.1.1,<4.0.0)
Requires-Dist: mkdocs (>=1.6.1,<2.0.0)
Requires-Dist: mkdocs-material (==9.6.12)
Requires-Dist: mkdocstrings[python] (>=0.29.1,<0.30.0)
Requires-Dist: numpy (>=1.26.0,<2.0.0)
Requires-Dist: pandas (>=2.0.0,<3.0.0)
Requires-Dist: scikit-learn (>=1.4.1.post1,<2.0.0)
Requires-Dist: scipy (>=1.11.1,<2.0.0)
Requires-Dist: werkzeug (>=3.1.3)
Requires-Dist: xlrd (>=2.0.1,<3.0.0)
